{
  "8b998fae-f7a6-434a-a8c2-79d853247782": {
    "title": "Beauty and the Beast (1991)",
    "slug": "beauty-and-the-beast-1991",
    "url": "3oEh78YRc9VN",
    "duration": "5222.050166",
    "scenes": [
      {
        "start": "735",
        "end": "835.5"
      },
      {
        "start": "986.6",
        "end": "1052"
      },
      {
        "start": "1377.8",
        "end": "1601"
      },
      {
        "start": "2757.9",
        "end": "3072"
      },
      {
        "start": "4301.2",
        "end": "4483.8"
      }
    ]
  },
  "ffc06e7f-8122-4d5d-8b87-b4cc8d830136": {
    "title": "Fantasia",
    "slug": "fantasia",
    "url": "7lt6sjm8nbud",
    "duration": "7579.530291",
    "scenes": [
      {
        "start": "2347",
        "end": "4006"
      },
      {
        "start": "6558",
        "end": "7309"
      }
    ]
  },
  "8e06a8b7-d667-4e31-939d-f40a6dd78a88": {
    "title": "Frozen",
    "slug": "frozen",
    "url": "4uKGzAJi3ROz",
    "duration": "6327.571249",
    "scenes": [
      {
        "start": "2511.8",
        "end": "2660"
      },
      {
        "start": "3494.8",
        "end": "3655"
      },
      {
        "start": "4193",
        "end": "4331"
      },
      {
        "start": "4985.6",
        "end": "5251"
      }
    ]
  },
  "42dc2dbf-331d-4665-8746-de2ac6d1f9a2": {
    "title": "Moana",
    "slug": "moana",
    "url": "70GoJHflgHH9",
    "duration": "6463.248458",
    "scenes": [
      {
        "start": "164.7",
        "end": "185"
      },
      {
        "start": "1579.4",
        "end": "1590.2"
      },
      {
        "start": "4370.5",
        "end": "4544"
      },
      {
        "start": "5001.9",
        "end": "5390"
      }
    ]
  }
}
